{
    "configurations": [
        {
            "name": "Win32",
            "includePath": [
                "C:\\Users\\koen\\.platformio\\packages\\framework-arduinoespressif8266\\tools\\sdk\\include",
                "C:\\Users\\koen\\.platformio\\packages\\framework-arduinoespressif8266\\tools\\sdk\\lwip\\include",
                "C:\\Users\\koen\\.platformio\\packages\\framework-arduinoespressif8266\\cores\\esp8266",
                "C:\\Users\\koen\\.platformio\\packages\\framework-arduinoespressif8266\\variants\\thing",
                "c:\\Users\\koen\\Documents\\Timelab\\Adem\\ADEM\\adem\\libraries\\Sensor",
                "c:\\Users\\koen\\Documents\\Timelab\\Adem\\ADEM\\adem\\libraries\\StoreAndForward",
                "c:\\Users\\koen\\Documents\\Timelab\\Adem\\ADEM\\adem\\libraries\\espsoftwareserial",
                "c:\\Users\\koen\\Documents\\Timelab\\Adem\\ADEM\\adem\\libraries\\TinyGPSPlus",
                "c:\\Users\\koen\\Documents\\Timelab\\Adem\\ADEM\\adem\\libraries\\ArduinoJson",
                "c:\\Users\\koen\\Documents\\Timelab\\Adem\\ADEM\\adem\\libraries\\gps_SwSerial",
                "C:\\Users\\koen\\.platformio\\packages\\framework-arduinoespressif8266\\libraries\\ESP8266WiFi\\src",
                "C:\\Users\\koen\\.platformio\\packages\\framework-arduinoespressif8266\\libraries\\DNSServer\\src",
                "C:\\Users\\koen\\.platformio\\packages\\framework-arduinoespressif8266\\libraries\\Wire",
                "c:\\Users\\koen\\Documents\\Timelab\\Adem\\ADEM\\adem\\libraries\\I2Cdev",
                "c:\\Users\\koen\\Documents\\Timelab\\Adem\\ADEM\\adem\\libraries\\Arduino_MPU-6050",
                "c:\\Users\\koen\\Documents\\Timelab\\Adem\\ADEM\\adem\\libraries\\RemoteDebug",
                "c:\\Users\\koen\\Documents\\Timelab\\Adem\\ADEM\\adem\\libraries\\accelero_MPU6050",
                "c:\\Users\\koen\\Documents\\Timelab\\Adem\\ADEM\\adem\\libraries\\battery_lipo",
                "c:\\Users\\koen\\Documents\\Timelab\\Adem\\ADEM\\adem\\libraries\\Adafruit_NeoPixel",
                "c:\\Users\\koen\\Documents\\Timelab\\Adem\\ADEM\\adem\\libraries\\led_NeoPixel",
                "c:\\Users\\koen\\Documents\\Timelab\\Adem\\ADEM\\adem\\libraries\\gps_I2C",
                "c:\\Users\\koen\\Documents\\Timelab\\Adem\\ADEM\\adem\\libraries\\TickerSchedlr",
                "c:\\Users\\koen\\Documents\\Timelab\\Adem\\ADEM\\adem\\libraries\\buzzer_passive",
                "c:\\Users\\koen\\Documents\\Timelab\\Adem\\ADEM\\adem\\libraries\\humidity_HTU21D",
                "c:\\Users\\koen\\Documents\\Timelab\\Adem\\ADEM\\adem\\libraries\\particulate_PPD42",
                "C:\\Users\\koen\\.platformio\\packages\\framework-arduinoespressif8266\\libraries\\ESP8266WebServer\\src",
                "c:\\Users\\koen\\Documents\\Timelab\\Adem\\ADEM\\adem\\libraries\\WiFiManager",
                "c:\\Users\\koen\\Documents\\Timelab\\Adem\\ADEM\\adem\\libraries\\barometer_BMP085",
                "c:\\Users\\koen\\Documents\\Timelab\\Adem\\ADEM\\adem\\libraries\\wifi_WiFiManager",
                "C:\\Users\\koen\\.platformio\\packages\\framework-arduinoespressif8266\\libraries\\ESP8266mDNS",
                "c:\\Users\\koen\\Documents\\Timelab\\Adem\\ADEM\\adem",
                "C:\\Users\\koen\\.platformio\\packages\\framework-arduinoespressif8266\\libraries\\ArduinoOTA",
                "C:\\Users\\koen\\.platformio\\packages\\framework-arduinoespressif8266\\libraries\\EEPROM",
                "C:\\Users\\koen\\.platformio\\packages\\framework-arduinoespressif8266\\libraries\\ESP8266AVRISP\\src",
                "C:\\Users\\koen\\.platformio\\packages\\framework-arduinoespressif8266\\libraries\\ESP8266HTTPClient\\src",
                "C:\\Users\\koen\\.platformio\\packages\\framework-arduinoespressif8266\\libraries\\ESP8266HTTPUpdateServer\\src",
                "C:\\Users\\koen\\.platformio\\packages\\framework-arduinoespressif8266\\libraries\\ESP8266SSDP",
                "C:\\Users\\koen\\.platformio\\packages\\framework-arduinoespressif8266\\libraries\\ESP8266WiFiMesh\\src",
                "C:\\Users\\koen\\.platformio\\packages\\framework-arduinoespressif8266\\libraries\\ESP8266httpUpdate\\src",
                "C:\\Users\\koen\\.platformio\\packages\\framework-arduinoespressif8266\\libraries\\Ethernet\\src",
                "C:\\Users\\koen\\.platformio\\packages\\framework-arduinoespressif8266\\libraries\\GDBStub\\src",
                "C:\\Users\\koen\\.platformio\\packages\\framework-arduinoespressif8266\\libraries\\Hash\\src",
                "C:\\Users\\koen\\.platformio\\packages\\framework-arduinoespressif8266\\libraries\\SD\\src",
                "C:\\Users\\koen\\.platformio\\packages\\framework-arduinoespressif8266\\libraries\\SPI",
                "C:\\Users\\koen\\.platformio\\packages\\framework-arduinoespressif8266\\libraries\\Servo\\src",
                "C:\\Users\\koen\\.platformio\\packages\\framework-arduinoespressif8266\\libraries\\SoftwareSerial",
                "C:\\Users\\koen\\.platformio\\packages\\framework-arduinoespressif8266\\libraries\\TFT_Touch_Shield_V2",
                "C:\\Users\\koen\\.platformio\\packages\\framework-arduinoespressif8266\\libraries\\Ticker",
                "C:\\Users\\koen\\.platformio\\packages\\framework-arduinoespressif8266\\libraries\\esp8266\\src",
                "C:\\Users\\koen\\.platformio\\packages\\toolchain-xtensa\\xtensa-lx106-elf\\include",
                "C:\\Users\\koen\\.platformio\\packages\\toolchain-xtensa\\lib\\gcc\\xtensa-lx106-elf\\4.8.2\\include",
                "C:\\Users\\koen\\.platformio\\packages\\toolchain-xtensa\\lib\\gcc\\xtensa-lx106-elf\\4.8.2\\include-fixed"
            ],
            "browse": {
                "limitSymbolsToIncludedHeaders": false,
                "path": [
                    "C:\\Users\\koen\\.platformio\\packages\\framework-arduinoespressif8266\\tools\\sdk\\include",
                    "C:\\Users\\koen\\.platformio\\packages\\framework-arduinoespressif8266\\tools\\sdk\\lwip\\include",
                    "C:\\Users\\koen\\.platformio\\packages\\framework-arduinoespressif8266\\cores\\esp8266",
                    "C:\\Users\\koen\\.platformio\\packages\\framework-arduinoespressif8266\\variants\\thing",
                    "c:\\Users\\koen\\Documents\\Timelab\\Adem\\ADEM\\adem\\libraries\\Sensor",
                    "c:\\Users\\koen\\Documents\\Timelab\\Adem\\ADEM\\adem\\libraries\\StoreAndForward",
                    "c:\\Users\\koen\\Documents\\Timelab\\Adem\\ADEM\\adem\\libraries\\espsoftwareserial",
                    "c:\\Users\\koen\\Documents\\Timelab\\Adem\\ADEM\\adem\\libraries\\TinyGPSPlus",
                    "c:\\Users\\koen\\Documents\\Timelab\\Adem\\ADEM\\adem\\libraries\\ArduinoJson",
                    "c:\\Users\\koen\\Documents\\Timelab\\Adem\\ADEM\\adem\\libraries\\gps_SwSerial",
                    "C:\\Users\\koen\\.platformio\\packages\\framework-arduinoespressif8266\\libraries\\ESP8266WiFi\\src",
                    "C:\\Users\\koen\\.platformio\\packages\\framework-arduinoespressif8266\\libraries\\DNSServer\\src",
                    "C:\\Users\\koen\\.platformio\\packages\\framework-arduinoespressif8266\\libraries\\Wire",
                    "c:\\Users\\koen\\Documents\\Timelab\\Adem\\ADEM\\adem\\libraries\\I2Cdev",
                    "c:\\Users\\koen\\Documents\\Timelab\\Adem\\ADEM\\adem\\libraries\\Arduino_MPU-6050",
                    "c:\\Users\\koen\\Documents\\Timelab\\Adem\\ADEM\\adem\\libraries\\RemoteDebug",
                    "c:\\Users\\koen\\Documents\\Timelab\\Adem\\ADEM\\adem\\libraries\\accelero_MPU6050",
                    "c:\\Users\\koen\\Documents\\Timelab\\Adem\\ADEM\\adem\\libraries\\battery_lipo",
                    "c:\\Users\\koen\\Documents\\Timelab\\Adem\\ADEM\\adem\\libraries\\Adafruit_NeoPixel",
                    "c:\\Users\\koen\\Documents\\Timelab\\Adem\\ADEM\\adem\\libraries\\led_NeoPixel",
                    "c:\\Users\\koen\\Documents\\Timelab\\Adem\\ADEM\\adem\\libraries\\gps_I2C",
                    "c:\\Users\\koen\\Documents\\Timelab\\Adem\\ADEM\\adem\\libraries\\TickerSchedlr",
                    "c:\\Users\\koen\\Documents\\Timelab\\Adem\\ADEM\\adem\\libraries\\buzzer_passive",
                    "c:\\Users\\koen\\Documents\\Timelab\\Adem\\ADEM\\adem\\libraries\\humidity_HTU21D",
                    "c:\\Users\\koen\\Documents\\Timelab\\Adem\\ADEM\\adem\\libraries\\particulate_PPD42",
                    "C:\\Users\\koen\\.platformio\\packages\\framework-arduinoespressif8266\\libraries\\ESP8266WebServer\\src",
                    "c:\\Users\\koen\\Documents\\Timelab\\Adem\\ADEM\\adem\\libraries\\WiFiManager",
                    "c:\\Users\\koen\\Documents\\Timelab\\Adem\\ADEM\\adem\\libraries\\barometer_BMP085",
                    "c:\\Users\\koen\\Documents\\Timelab\\Adem\\ADEM\\adem\\libraries\\wifi_WiFiManager",
                    "C:\\Users\\koen\\.platformio\\packages\\framework-arduinoespressif8266\\libraries\\ESP8266mDNS",
                    "c:\\Users\\koen\\Documents\\Timelab\\Adem\\ADEM\\adem",
                    "C:\\Users\\koen\\.platformio\\packages\\framework-arduinoespressif8266\\libraries\\ArduinoOTA",
                    "C:\\Users\\koen\\.platformio\\packages\\framework-arduinoespressif8266\\libraries\\EEPROM",
                    "C:\\Users\\koen\\.platformio\\packages\\framework-arduinoespressif8266\\libraries\\ESP8266AVRISP\\src",
                    "C:\\Users\\koen\\.platformio\\packages\\framework-arduinoespressif8266\\libraries\\ESP8266HTTPClient\\src",
                    "C:\\Users\\koen\\.platformio\\packages\\framework-arduinoespressif8266\\libraries\\ESP8266HTTPUpdateServer\\src",
                    "C:\\Users\\koen\\.platformio\\packages\\framework-arduinoespressif8266\\libraries\\ESP8266SSDP",
                    "C:\\Users\\koen\\.platformio\\packages\\framework-arduinoespressif8266\\libraries\\ESP8266WiFiMesh\\src",
                    "C:\\Users\\koen\\.platformio\\packages\\framework-arduinoespressif8266\\libraries\\ESP8266httpUpdate\\src",
                    "C:\\Users\\koen\\.platformio\\packages\\framework-arduinoespressif8266\\libraries\\Ethernet\\src",
                    "C:\\Users\\koen\\.platformio\\packages\\framework-arduinoespressif8266\\libraries\\GDBStub\\src",
                    "C:\\Users\\koen\\.platformio\\packages\\framework-arduinoespressif8266\\libraries\\Hash\\src",
                    "C:\\Users\\koen\\.platformio\\packages\\framework-arduinoespressif8266\\libraries\\SD\\src",
                    "C:\\Users\\koen\\.platformio\\packages\\framework-arduinoespressif8266\\libraries\\SPI",
                    "C:\\Users\\koen\\.platformio\\packages\\framework-arduinoespressif8266\\libraries\\Servo\\src",
                    "C:\\Users\\koen\\.platformio\\packages\\framework-arduinoespressif8266\\libraries\\SoftwareSerial",
                    "C:\\Users\\koen\\.platformio\\packages\\framework-arduinoespressif8266\\libraries\\TFT_Touch_Shield_V2",
                    "C:\\Users\\koen\\.platformio\\packages\\framework-arduinoespressif8266\\libraries\\Ticker",
                    "C:\\Users\\koen\\.platformio\\packages\\framework-arduinoespressif8266\\libraries\\esp8266\\src",
                    "C:\\Users\\koen\\.platformio\\packages\\toolchain-xtensa\\xtensa-lx106-elf\\include",
                    "C:\\Users\\koen\\.platformio\\packages\\toolchain-xtensa\\lib\\gcc\\xtensa-lx106-elf\\4.8.2\\include",
                    "C:\\Users\\koen\\.platformio\\packages\\toolchain-xtensa\\lib\\gcc\\xtensa-lx106-elf\\4.8.2\\include-fixed"
                ]
            }
        }
    ]
}